django_dnf/__init__.py
django_dnf/fields.py
django_dnf/formfields.py
django_dnf/models.py
django_dnf/validators.py
django_dnf/tests/__init__.py
django_dnf/tests/models.py
django_dnf/tests/test_fields.py
django_domainname-0.1.1.dist-info/LICENSE
django_domainname-0.1.1.dist-info/METADATA
django_domainname-0.1.1.dist-info/WHEEL
django_domainname-0.1.1.dist-info/top_level.txt
django_domainname-0.1.1.dist-info/RECORD
