Metadata-Version: 2.1
Name: django-domainname
Version: 0.1.1
Summary: Domain name model field and form field for Django.
Home-page: https://github.com/MehdioKhan/django-domainname
Author: Mahdi Khanmohammadi
Author-email: mehdiokhan@gmail.com
License: GNU License
Platform: UNKNOWN
Classifier: Development Status :: 5 - Production/Stable
Classifier: Framework :: Django
Classifier: Intended Audience :: Developers
Classifier: License :: OSI Approved :: BSD License
Classifier: Operating System :: OS Independent
Classifier: Programming Language :: Python
Classifier: Programming Language :: Python :: 2
Classifier: Programming Language :: Python :: 3
Classifier: Topic :: Internet :: WWW/HTTP
